{
  "nav": {
    "home": "Hem",
    "map": "Karta",
    "trains": "Tåg",
    "about": "Om oss"
  },
  "search": {
    "placeholder": "Sök stationer...",
    "station": "Station",
    "train": "Tåg",
    "trainNotFound": "Tåget hittades inte."
  },
  "station": {
    "title": "Tidtabell: {station}",
    "arrivals": "Ankomster",
    "departures": "Avgångar",
    "arrival": "Ankomst",
    "departure": "Avgång",
    "track": "Spår",
    "time": "Tid",
    "actual": "Realtid"
  },
  "train": {
    "details": "Tåg {type} {number}",
    "timetable": "Tidtabell",
    "route": "Rutt",
    "composition": "Tågtilldelning",
    "speed": "Max hastighet: {speed} km/h",
    "length": "Längd: {length} m",
    "cancelled": "Inställt"
  },
  "common": {
    "date": "Datum",
    "prevDay": "Föregående dag",
    "nextDay": "Nästa dag",
    "loading": "Laddar data...",
    "noData": "Inget att visa"
  },
  "about": {
    "title": "Ursprungliga datakällor",
    "license": "licens"
  },
  "map": {
    "title": "Livekarta",
    "train": "Tåg",
    "dataFetched": "Kartdata hämtad",
    "speed": "Hastighet",
    "bearing": "Riktning",
    "lastUpdated": "Senast uppdaterad"
  }
}